{
  "0": ["bVtxCL", "kstTMass", "bCosAlphaBS", "bLBSs", "bDCABSs", "kstTrkpDCABSs", "kstTrkmDCABSs"],

  "1": ["bVtxCL", "kstTMass", "bCosAlphaBS", "bLBSs", "bDCABSs", "kstTrkpDCABSs", "kstTrkmDCABSs",
        "muLeadingPt", "muTrailingPt"],

  "2": ["bVtxCL", "kstTMass", "bCosAlphaBS", "bLBSs", "bDCABSs", "kstTrkpDCABSs", "kstTrkmDCABSs",
        "muLeadingPt", "muTrailingPt", "kstTrkpPt", "kstTrkmPt"],

  "3": ["bVtxCL", "kstTMass", "bCosAlphaBS", "bLBSs", "bDCABSs", "kstTrkpDCABSs", "kstTrkmDCABSs",
        "muLeadingPtR", "muTrailingPtR", "kstTrkpPtR", "kstTrkmPtR"],

  "4": ["muLeadingPtR", "muTrailingPtR", "kstTrkpPtR", "kstTrkmPtR",
        "muLeadingPt", "muTrailingPt", "kstTrkpPt", "kstTrkmPt"],

  "5": ["bVtxCL", "kstTMass", "bCosAlphaBS", "bLBSs", "bDCABSs", "kstTrkpDCABSs", "kstTrkmDCABSs",
        "mumIsoPtR_dr04", "mupIsoPtR_dr04", "kstTrkmIsoPtR_dr04", "kstTrkpIsoPtR_dr04"],

  "6": ["bTMass", "bVtxCL", "bPt", "bPhi", "bEta",
        "kstTMass", "kstPt", "kstPhi", "kstEta",
        "mumuMass", "mumuPt", "mumuPhi", "mumuEta",
        "kstTrkmPt", "kstTrkmPhi", "kstTrkmEta", "kstTrkmDCABS",
        "kstTrkpPt", "kstTrkpPhi",  "kstTrkpEta", "kstTrkpDCABS",
        "mumPt", "mumPhi", "mumEta", 
        "mupPt", "mupPhi", "mupEta",
        "bCosAlphaBS", "bLBS", "bDCABS",
        "muLeadingPt", "muTrailingPt",
        "bLBSs", "bDCABSs",
        "kstTrkmDCABSs", "kstTrkpDCABSs",
        "kstTrkpPtR", "kstTrkmPtR", "muTrailingPtR", "muLeadingPtR",
        "mumuPtR", "kstPtR",
        "mumIsoPt_dr04", "mupIsoPt_dr04", "kstTrkmIsoPt_dr04", "kstTrkpIsoPt_dr04",
        "mumIsoPtR_dr04", "mupIsoPtR_dr04", "kstTrkmIsoPtR_dr04", "kstTrkpIsoPtR_dr04",
        "IsoPtR_dr04_sum"],

  "7": ["bVtxCL", "bPt", "bPhi", "bEta",
        "kstTMass", "kstPt", "kstPhi", "kstEta",
        "mumuMass", "mumuPt", "mumuPhi", "mumuEta",
        "kstTrkmPt", "kstTrkmPhi", "kstTrkmEta", "kstTrkmDCABS",
        "kstTrkpPt", "kstTrkpPhi",  "kstTrkpEta", "kstTrkpDCABS",
        "mumPt", "mumPhi", "mumEta", 
        "mupPt", "mupPhi", "mupEta",
        "bCosAlphaBS", "bLBS", "bDCABS",
        "muLeadingPt", "muTrailingPt",
        "bLBSs", "bDCABSs",
        "kstTrkmDCABSs", "kstTrkpDCABSs",
        "kstTrkpPtR", "kstTrkmPtR", "muTrailingPtR", "muLeadingPtR",
        "mumuPtR", "kstPtR",
        "mumIsoPt_dr04", "mupIsoPt_dr04", "kstTrkmIsoPt_dr04", "kstTrkpIsoPt_dr04",
        "mumIsoPtR_dr04", "mupIsoPtR_dr04", "kstTrkmIsoPtR_dr04", "kstTrkpIsoPtR_dr04",
        "IsoPtR_dr04_sum"],

  "8": ["bPt", "bLBSs", "kstPt", "bCosAlphaBS", "kstTrkmDCABSs", "kstTrkpIsoPtR_dr04", "mumPt", "mumuPt", "mupPt", 
        "bDCABSs", "kstTrkpPt", "bVtxCL", "kstTrkmIsoPtR_dr04", "muLeadingPt"],

  "9": ["bPt", "bLBSs", "kstPt", "bCosAlphaBS", "mumPt", "kstTrkpIsoPtR_dr04", "mupPt", "mumuPt"],

  "10": ["bTMass","bVtxCL", "kstTMass", "kstPt", "kstTrkmPt", "kstTrkmDCABS", "kstTrkpPt", "kstTrkpDCABS",
        "mumPt", "mupPt", "bCosAlphaBS", "bLBS", "bDCABS", "muLeadingPt", "muTrailingPt",
        "bLBSs", "bDCABSs", "kstTrkmDCABSs", "kstTrkpDCABSs", "kstTrkpPtR", "kstTrkmPtR", 
        "muTrailingPtR", "muLeadingPtR", "mumuPtR", "kstPtR","mumIsoPtR_dr04", "mupIsoPtR_dr04", 
        "kstTrkmIsoPtR_dr04", "kstTrkpIsoPtR_dr04", "IsoPtR_dr04_sum"],
      
  "11": ["bVtxCL", "kstTMass", "kstPt", "kstTrkmPt", "kstTrkmDCABS", "kstTrkpPt", "kstTrkpDCABS",
        "mumPt", "mupPt", "bCosAlphaBS", "bLBS", "bDCABS", "muLeadingPt", "muTrailingPt",
        "bLBSs", "bDCABSs", "kstTrkmDCABSs", "kstTrkpDCABSs", "kstTrkpPtR", "kstTrkmPtR", 
        "muTrailingPtR", "muLeadingPtR", "mumuPtR", "kstPtR","mumIsoPtR_dr04", "mupIsoPtR_dr04", 
        "kstTrkmIsoPtR_dr04", "kstTrkpIsoPtR_dr04", "IsoPtR_dr04_sum"],
      
  "12": ["kstPt", "bLBSs", "bCosAlphaBS", "IsoPtR_dr04_sum", "bVtxCL", "bDCABSs", "kstTrkmDCABSs", 
        "kstTrkpDCABSs", "kstTrkpIsoPtR_dr04", "kstTrkmIsoPtR_dr04", "muTrailingPt", "mupIsoPtR_dr04"],

  "13": ["bVtxCL", "kstTMass", "kstPt", "kstTrkmPt", "kstTrkpPt", "bCosAlphaBS", "muLeadingPt", "bLBSs", 
         "kstTrkmDCABSs", "kstTrkpPtR", "kstTrkmPtR", "mumuPtR", "mupIsoPtR_dr04", "kstTrkpIsoPtR_dr04"],

  "14": ["kstPt", "bLBSs", "bCosAlphaBS", "IsoPtR_dr04_sum", "bVtxCL", "bDCABSs", "kstTrkmDCABSs", "kstTrkpDCABSs", 
         "kstTrkpIsoPtR_dr04", "muTrailingPt", "mupIsoPtR_dr04", "mumIsoPtR_dr04", "kstTrkpPt", "mumPt"]
        
}